{
  "demons": [
     {
      "id": "theredrealm",
      "name": "The Red Realm",
      "creator": "faquteam",
      "videoUrl": "https://drive.google.com/file/d/1jktPsHjEkSmBTTQVRpQYDQQ0Pv2Bnx-n/view",
      "image": "images/theredrealm.png",
      "description": "Экстрим демон от команды FaquTeam.(https://drive.google.com/file/d/1jktPsHjEkSmBTTQVRpQYDQQ0Pv2Bnx-n/view) верификация на гугл диске."
    },
    {
      "id": "gypers",
      "name": "Gypers",
      "creator": "WeztT",
      "videoUrl": "https://youtu.be/-ZsZh7wsbjA",
      "image": "images/gypers.png",
      "description": "Бывший топ 1."
    },
    {
      "id": "uauafactorial",
      "name": "UaUa Factorial",
      "creator": "Dodjeman55",
      "videoUrl": "https://youtu.be/-ZsZh7wsbjA",
      "image": "images/uauafactorial.png",
      "description": "NK демон. (https://drive.google.com/file/d/1IALF4Reh0u5Y4ndQU-VQrkBH37xyGxiK/view?usp=drivesdk)"
    },
    {
      "id": "unamaded",
      "name": "Unmaded",
      "creator": "Naz0rro",
      "videoUrl": "https://youtu.be/-ZsZh7wsbjA",
      "image": "images/unnamed.png",
      "description": "Баллистик вистфулли."
    },
    {
      "id": "rip",
      "name": "RIP",
      "creator": "Ariller",
      "videoUrl": "https://youtu.be/-ZsZh7wsbjA",
      "image": "images/rip.png",
      "description": "Прохождение (https://drive.google.com/file/d/1E66OevrF3JXSeSdbqWZmsLyQVnNC7MFD/view?usp=sharing)"
    },
    {
      "id": "oldamethyst",
      "name": "Old Amethyst",
      "creator": "To4nowhy",
      "videoUrl": "https://youtu.be/-ZsZh7wsbjA",
      "image": "images/oldamethyst.png",
      "description": ""
    },
     {
      "id": "heliorobot",
      "name": "HelioRobot",
      "creator": "Sayori",
      "videoUrl": "https://youtu.be/XxAyFRy_ET8?si=HCNfCGWAH-2mR5__",
      "image": "images/oldamethyst.png",
      "description": ""
    }
  ]
}
