{
  "impossibleDemons": [
    {
      "id": "mindless",
      "name": "MINDLESS",
      "creator": "VXMNC",
      "videoUrl": "https://youtu.be/JtJa9tCkzj8",
      "tags": ["Epic Decorations", "15+ CPS", "Memory", "Humanly impossible", "Ship", "Cube", "Spam"],
      "image": "",
      "description": ""
    },
      {
      "id": "limbo",
      "name": "Limbo",
      "creator": "VXMNC",
      "videoUrl": "https://youtu.be/45mbzJJBbd8",
      "tags": ["Featured Decorations", "15+ CPS", "Memory", "Humanly impossible", "Ship"],
      "image": "",
      "description": ""
    },
     {
      "id": "bleach",
      "name": "Bleach",
      "creator": "owokor",
      "videoUrl": "https://youtu.be/vbqbQ873JtU?si=IPSqcfkJxXOtDmWZ",
       "tags": ["Featured Decorations", "Humanly impossible", "consistency", "Wave"],
      "image": "",
      "description": ""
    },
     {
      "id": "sd fcghjewkl;",
      "name": "sd fcghjewkl;",
      "creator": "heroinpro",
      "videoUrl": "https://youtu.be/j-6dReVGjsY",
       "tags": ["Starrate Decorations", "Humanly impossible", "Timing", "Cube", "Wave", "Spam"],
      "image": "",
      "description": ""
    },
     {
      "id": "Abaddon",
      "name": "Abaddon",
      "creator": "Royal",
      "videoUrl": "https://youtu.be/7dtJgxNoP_I?si=qyO2kzCcXT2H9zHa",
       "tags": ["Epic Decorations", "Humanly impossible", "consistency", "Wave"],
      "image": "",
      "description": ""
    },
     {
      "id": "samsungs215g",
      "name": "Samsung S21 5G",
      "creator": "VladGMD",
      "videoUrl": "https://youtu.be/deCHB-zmZnM",
       "tags": ["Featured Decorations", "Wave", "NC"],
      "image": "images/samsungs215g.jpg",
      "description": ""
    },
     {
      "id": "projectionfailure",
      "name": "Projection Failure",
      "creator": "TecnoKnight",
      "videoUrl": "https://youtu.be/S2qZlyp5pWw?si=nXXZA1OU4qyfQhZv",
       "tags": ["Featured Decorations"],
      "image": "images/projectionfailure.jpg",
      "description": ""
    }
  ]
}
